{
  "date_created": "2023-04-28T18:05:18.000Z",
  "audio_download_size_string": "8.2 MB",
  "audio_download_size": 8189097,
  "auto_display": true,
  "bitly_audio": "https://mytat.me/a235558",
  "bitly_video": "https://mytat.me/v235558",
  "category": 23,
  "clip_link": null,
  "clip_parent": null,
  "clip_title": null,
  "clipper_email": null,
  "date_recorded": "2023-04-28",
  "dedication": null,
  "display_active": true,
  "duration": 976,
  "event_speakers": [],
  "host": 0,
  "id": 235558,
  "id_md5": null,
  "is_clip": null,
  "is_short": false,
  "jwplayer_mediaId": "p5l74CSA",
  "ladies": false,
  "language": 1,
  "lecture_url": null,
  "location": 2,
  "media": "235558--____03_05_2023__eb09ed8d-e7eb-446e-853c-1898df6a8c7d.mp4",
  "meta_tag": "fdadb594d1e91b02db50253ff8b16a1dfd95aa24",
  "no_download": null,
  "on_recent_list": true,
  "org": 0,
  "original_file": "Daniel__Glatstein__04_28_2023__fdadb594d1e91b02db50253ff8b16a1dfd95aa24.mp4",
  "phone_system_short_extension": "335504",
  "private": false,
  "private_code": null,
  "published_by": 13925,
  "published_by_name": "glatsteintat@gmail.com",
  "slug": "pninei-maggid-harakiah-original-insights-on-parashat-kedoshim-plus-an-imponderable",
  "speaker": 105,
  "subcategory": 74,
  "text": null,
  "thumbnail": "1662715663-031cb5a4a33a071f72a7d0bb4d9c34f701cd74fe1371cf72a356df6fe10438bb-d",
  "thumbnail_url": "https://ta-lectures.s3.us-east-005.backblazeb2.com/thumbnails/235558/235558.jpg",
  "title": "Pninei Maggid Harakiah- Original Insights on Parashat Kedoshim {plus an Imponderable}",
  "title_rtl": false,
  "desc": null,
  "video_download_size_string": "87.91MB",
  "video_download_size": 92181730,
  "vimeo_video": "vimeo_002---/videos/822119184",
  "vimeo_video_links": [
    "https://proxier.torahanytime.com/aHR0cHM6Ly90YS1sZWN0dXJlcy5zMy51cy1lYXN0LTAwNS5iYWNrYmxhemViMi5jb20vbXA0LzIzNTU1OC5tcDQ/e2bf408d30590c9638ada0ecbf986d7271eddc8aec4d2af8753319493a78fd8d.mp4?has_women=0&speaker_id=105&digest=3c28011974e93ebe6d64d57a849b0102cfec91423318939a52dae604584919ad"
  ],
  "vimeo_video_links_legacy": [
    "https://player.vimeo.com/progressive_redirect/playback/822119184/rendition/360p/file.mp4?loc=external&oauth2_token_id=1080790441&signature=97382508760296a253ec52b776bac465bcf11c189cd35a6e1a286e1fc83c8a5e",
    "https://player.vimeo.com/external/822119184.m3u8?s=b61296d0e5ed5ce409ff1dbb2735e41ff7e2c19d&oauth2_token_id=1080790441"
  ],
  "vimeo_hash": "4fa2634d36",
  "box_id": 1202193139825,
  "publish_by_date": null,
  "date_to_show": "2023-04-28T18:05:18.000Z",
  "is_only_watchable_by_female": false,
  "is_only_listenable_by_female": false,
  "is_only_discoverable_by_female": false,
  "is_only_discoverable_within_org": false,
  "is_not_discoverable": false,
  "m3u8_url": null,
  "mp4_url": "https://ta-lectures.s3.us-east-005.backblazeb2.com/mp4/235558.mp4",
  "mp3_url": "https://dl.torahanytime.com/mp3/235558--____03_05_2023__eb09ed8d-e7eb-446e-853c-1898df6a8c7d.mp4.mp3",
  "watermarked_original_mp4_url": null,
  "ragie_document_id": "7fc7e809-ff69-4a8d-8339-e47bcfb38b6f",
  "created_at": "2023-04-28T18:05:18.000Z",
  "updated_at": "2025-04-29T22:54:24.000Z",
  "deleted_at": null,
  "subcategories": [
    {
      "id": 74,
      "name": "Kedoshim",
      "english_name": null
    }
  ],
  "parent_info": null,
  "projects": [
    {
      "id": 1,
      "name": "TorahAnytime"
    }
  ],
  "categories": [
    {
      "id": 23,
      "name": "Parasha/Torah Portion",
      "english_name": "Torah"
    }
  ],
  "language_name": "English",
  "speaker_name_first": "Daniel",
  "speaker_name_last": "Glatstein",
  "speaker_photo": "r-daniel-glatstein_2eb5b66c-da88-4cff-a7ec-e55e1494ba84.jpg",
  "female": false,
  "view_female_level": 0,
  "speaker_no_download": 0,
  "speaker_title": "Rabbi",
  "speaker_title_short": "R'",
  "video_url": "https://ta-lectures.s3.us-east-005.backblazeb2.com/mp4/235558.mp4",
  "audio_url": "https://dl.torahanytime.com/mp3/235558--____03_05_2023__eb09ed8d-e7eb-446e-853c-1898df6a8c7d.mp4.mp3",
  "vimeo_video_id": "822119184",
  "proxy_mp4_url": "https://proxier.torahanytime.com/aHR0cHM6Ly90YS1sZWN0dXJlcy5zMy51cy1lYXN0LTAwNS5iYWNrYmxhemViMi5jb20vbXA0LzIzNTU1OC5tcDQ/e2bf408d30590c9638ada0ecbf986d7271eddc8aec4d2af8753319493a78fd8d.mp4?has_women=0&speaker_id=105&digest=3c28011974e93ebe6d64d57a849b0102cfec91423318939a52dae604584919ad",
  "likeCount": 2,
  "viewCount": 980
}