{
  "date_created": "2023-05-01T10:11:45.000Z",
  "audio_download_size_string": "5.7 MB",
  "audio_download_size": 5682928,
  "auto_display": true,
  "bitly_audio": "https://mytat.me/a235767",
  "bitly_video": "https://mytat.me/v235767",
  "category": 126,
  "clip_link": null,
  "clip_parent": null,
  "clip_title": null,
  "clipper_email": null,
  "date_recorded": "2023-04-30",
  "dedication": null,
  "display_active": true,
  "duration": 619,
  "event_speakers": null,
  "host": 0,
  "id": 235767,
  "id_md5": null,
  "is_clip": null,
  "is_short": false,
  "jwplayer_mediaId": "uLkM0aa7",
  "ladies": false,
  "language": 1,
  "lecture_url": null,
  "location": 3,
  "media": "235767--____04_01_2023__fbf266be-fca0-4d84-82cc-74710b334837.mp4",
  "meta_tag": "b20bb13cdd847cbb0baf01477a287238ea7fe455",
  "no_download": null,
  "on_recent_list": true,
  "org": 0,
  "original_file": "Yitzchok___Boehm__04_30_2023__b20bb13cdd847cbb0baf01477a287238ea7fe455.mp4",
  "phone_system_short_extension": "335766",
  "private": false,
  "private_code": null,
  "published_by": 11172,
  "published_by_name": "Nesanel Epstein",
  "slug": "mishna-berurah-1251-2-hopping-and-skipping-during-kedusha",
  "speaker": 797,
  "subcategory": 161,
  "text": null,
  "thumbnail": "1663678333-ae7ce0ce8136c71500d41e31932a1085bf4284aae8e6e76a05830274a0d18755-d",
  "thumbnail_url": "https://ta-lectures.s3.us-east-005.backblazeb2.com/thumbnails/235767/235767.jpg",
  "title": "Mishna Berurah 125:1-2 Hopping and Skipping During Kedusha",
  "title_rtl": false,
  "desc": null,
  "video_download_size_string": "23.56MB",
  "video_download_size": 24702699,
  "vimeo_video": "vimeo_002---/videos/822649326",
  "vimeo_video_links": [
    "https://proxier.torahanytime.com/aHR0cHM6Ly90YS1sZWN0dXJlcy5zMy51cy1lYXN0LTAwNS5iYWNrYmxhemViMi5jb20vbXA0LzIzNTc2Ny5tcDQ/aea84fb47bea6ddb6c040faf6cf31354169bdf3a3f8a698f1f41972b277e4db5.mp4?has_women=0&speaker_id=797&digest=45d732a1e1fda32269ea0c986064be9523f78a7f1437088dcc37514b51cb502e"
  ],
  "vimeo_video_links_legacy": [
    "https://player.vimeo.com/progressive_redirect/playback/822649326/rendition/360p/file.mp4?loc=external&oauth2_token_id=1080790441&signature=031b43c454101af17a587a14d6dbdef56ab63a30040fde5f4683d009b3363beb",
    "https://player.vimeo.com/progressive_redirect/playback/822649326/rendition/240p/file.mp4?loc=external&oauth2_token_id=1080790441&signature=12b70f55a6c697d7c3107ad94c495e1f661e0e6836912a25f0a23850ae34cd79",
    "https://player.vimeo.com/external/822649326.m3u8?s=68aed80f0c0031aea3d0880fd28b30d63cc16745&oauth2_token_id=1080790441"
  ],
  "vimeo_hash": "2be07e3b91",
  "box_id": 1203766639342,
  "publish_by_date": null,
  "date_to_show": "2023-05-01T10:11:45.000Z",
  "is_only_watchable_by_female": false,
  "is_only_listenable_by_female": false,
  "is_only_discoverable_by_female": false,
  "is_only_discoverable_within_org": false,
  "is_not_discoverable": false,
  "m3u8_url": null,
  "mp4_url": "https://ta-lectures.s3.us-east-005.backblazeb2.com/mp4/235767.mp4",
  "mp3_url": "https://dl.torahanytime.com/mp3/235767--____04_01_2023__fbf266be-fca0-4d84-82cc-74710b334837.mp4.mp3",
  "watermarked_original_mp4_url": null,
  "ragie_document_id": "4a2cac08-a304-4117-a814-7d5d42bcc450",
  "created_at": "2023-05-01T10:11:45.000Z",
  "updated_at": "2025-04-30T00:25:17.000Z",
  "deleted_at": null,
  "subcategories": [
    {
      "id": 161,
      "name": "Prayer",
      "english_name": null
    }
  ],
  "parent_info": null,
  "projects": [
    {
      "id": 1,
      "name": "TorahAnytime"
    }
  ],
  "categories": [
    {
      "id": 126,
      "name": "Halacha/Jewish Law",
      "english_name": null
    }
  ],
  "language_name": "English",
  "speaker_name_first": "Yitzchok ",
  "speaker_name_last": "Boehm",
  "speaker_photo": "",
  "female": false,
  "view_female_level": 0,
  "speaker_no_download": 0,
  "speaker_title": "Rabbi",
  "speaker_title_short": "R'",
  "video_url": "https://ta-lectures.s3.us-east-005.backblazeb2.com/mp4/235767.mp4",
  "audio_url": "https://dl.torahanytime.com/mp3/235767--____04_01_2023__fbf266be-fca0-4d84-82cc-74710b334837.mp4.mp3",
  "vimeo_video_id": "822649326",
  "proxy_mp4_url": "https://proxier.torahanytime.com/aHR0cHM6Ly90YS1sZWN0dXJlcy5zMy51cy1lYXN0LTAwNS5iYWNrYmxhemViMi5jb20vbXA0LzIzNTc2Ny5tcDQ/aea84fb47bea6ddb6c040faf6cf31354169bdf3a3f8a698f1f41972b277e4db5.mp4?has_women=0&speaker_id=797&digest=45d732a1e1fda32269ea0c986064be9523f78a7f1437088dcc37514b51cb502e",
  "likeCount": 0,
  "viewCount": 41
}