{
  "date_created": "2023-05-02T18:39:37.000Z",
  "audio_download_size_string": "8.8 MB",
  "audio_download_size": 8790510,
  "auto_display": true,
  "bitly_audio": "https://mytat.me/a236057",
  "bitly_video": "https://mytat.me/v236057",
  "category": 100053,
  "clip_link": null,
  "clip_parent": null,
  "clip_title": null,
  "clipper_email": null,
  "date_recorded": "2023-04-23",
  "dedication": null,
  "display_active": true,
  "duration": 1307,
  "event_speakers": [],
  "host": 0,
  "id": 236057,
  "id_md5": null,
  "is_clip": null,
  "is_short": false,
  "jwplayer_mediaId": "Ksf1Inuy",
  "ladies": false,
  "language": 1,
  "lecture_url": null,
  "location": 9,
  "media": "236057--____04_02_2023__7659df15-d84c-4d38-b6b3-b17dcd2b0604.mp4",
  "meta_tag": "7e350b36dde758fadb09ff22c1dfc76ee7f13852",
  "no_download": null,
  "on_recent_list": false,
  "org": 0,
  "original_file": "Yitzchok_Chaim_David__Cohen__04_23_2023__7e350b36dde758fadb09ff22c1dfc76ee7f13852.MOV",
  "phone_system_short_extension": "335992",
  "private": false,
  "private_code": null,
  "published_by": 200009,
  "published_by_name": "Dovid_Cohen161673899148311",
  "slug": "daf-yomi-yerushalmi-masechet-peah-chazarah-daf-43-to-47",
  "speaker": 1310,
  "subcategory": 0,
  "text": null,
  "thumbnail": "1664353121-e21f51cc75b2d03049eb3e21cc3c389d205a4b55a6cfbd474c9339dbc5a8ecd8-d",
  "thumbnail_url": "https://ta-lectures.s3.us-east-005.backblazeb2.com/thumbnails/236057/236057.jpg",
  "title": "Daf Yomi Yerushalmi: Masechet Peah - Chazarah Daf 43 to 47",
  "title_rtl": false,
  "desc": null,
  "video_download_size_string": "42.22MB",
  "video_download_size": 44269954,
  "vimeo_video": "vimeo_002---/videos/823108402",
  "vimeo_video_links": [
    "https://proxier.torahanytime.com/aHR0cHM6Ly90YS1sZWN0dXJlcy5zMy51cy1lYXN0LTAwNS5iYWNrYmxhemViMi5jb20vbXA0LzIzNjA1Ny5tcDQ/5885f9f5630ce8157af0802978f4fd8a81381a7f60ae50bc65155505592fbaaf.mp4?has_women=0&speaker_id=1310&digest=b7d15a483de02b4042dcea8dab12deb70d9dfdb175f9929098c36f764b83701e"
  ],
  "vimeo_video_links_legacy": [
    "https://player.vimeo.com/progressive_redirect/playback/823108402/rendition/360p/file.mp4?loc=external&oauth2_token_id=1080790441&signature=e9daa5a76795a02786aac61de828041c2072fb00b23188342e83f16b1708ddda",
    "https://player.vimeo.com/progressive_redirect/playback/823108402/rendition/240p/file.mp4?loc=external&oauth2_token_id=1080790441&signature=8a0a654026227bba26b5cd98975ed3b562aeff08487d3a99ad31af2c76eecc81",
    "https://player.vimeo.com/external/823108402.m3u8?s=4b9bf17f8a365fcb9528884b665b4324e0410f4e&oauth2_token_id=1080790441"
  ],
  "vimeo_hash": "463bd77f4c",
  "box_id": 1204860485529,
  "publish_by_date": null,
  "date_to_show": "2023-05-02T18:39:37.000Z",
  "is_only_watchable_by_female": false,
  "is_only_listenable_by_female": false,
  "is_only_discoverable_by_female": false,
  "is_only_discoverable_within_org": false,
  "is_not_discoverable": false,
  "m3u8_url": null,
  "mp4_url": "https://ta-lectures.s3.us-east-005.backblazeb2.com/mp4/236057.mp4",
  "mp3_url": "https://dl.torahanytime.com/mp3/236057--____04_02_2023__7659df15-d84c-4d38-b6b3-b17dcd2b0604.mp4.mp3",
  "watermarked_original_mp4_url": null,
  "ragie_document_id": "9100065b-c857-4778-acd5-c9b5a268b7a8",
  "created_at": "2023-05-02T18:39:37.000Z",
  "updated_at": "2025-04-30T02:15:59.000Z",
  "deleted_at": null,
  "subcategories": [],
  "parent_info": null,
  "projects": [
    {
      "id": 1,
      "name": "TorahAnytime"
    }
  ],
  "categories": [
    {
      "id": 100053,
      "name": "Daf Yerushalmi",
      "english_name": null
    }
  ],
  "language_name": "English",
  "speaker_name_first": "Yitzchok Chaim David",
  "speaker_name_last": "Cohen",
  "speaker_photo": "",
  "female": false,
  "view_female_level": 0,
  "speaker_no_download": 0,
  "speaker_title": "Rabbi",
  "speaker_title_short": "R'",
  "video_url": "https://ta-lectures.s3.us-east-005.backblazeb2.com/mp4/236057.mp4",
  "audio_url": "https://dl.torahanytime.com/mp3/236057--____04_02_2023__7659df15-d84c-4d38-b6b3-b17dcd2b0604.mp4.mp3",
  "vimeo_video_id": "823108402",
  "proxy_mp4_url": "https://proxier.torahanytime.com/aHR0cHM6Ly90YS1sZWN0dXJlcy5zMy51cy1lYXN0LTAwNS5iYWNrYmxhemViMi5jb20vbXA0LzIzNjA1Ny5tcDQ/5885f9f5630ce8157af0802978f4fd8a81381a7f60ae50bc65155505592fbaaf.mp4?has_women=0&speaker_id=1310&digest=b7d15a483de02b4042dcea8dab12deb70d9dfdb175f9929098c36f764b83701e",
  "likeCount": 0,
  "viewCount": 4
}