{
  "date_created": "2023-05-04T03:30:42.000Z",
  "audio_download_size_string": "7.1 MB",
  "audio_download_size": 7116294,
  "auto_display": true,
  "bitly_audio": "https://mytat.me/a236358",
  "bitly_video": "https://mytat.me/v236358",
  "category": 8,
  "clip_link": null,
  "clip_parent": null,
  "clip_title": null,
  "clipper_email": null,
  "date_recorded": "2023-05-02",
  "dedication": null,
  "display_active": true,
  "duration": 826,
  "event_speakers": null,
  "host": 8,
  "id": 236358,
  "id_md5": null,
  "is_clip": null,
  "is_short": false,
  "jwplayer_mediaId": "kE3n2yBL",
  "ladies": false,
  "language": 1,
  "lecture_url": null,
  "location": 2,
  "media": "236358--____04_04_2023__7bfd8ea5-650b-4517-951d-8d50c0d171a2.mp4",
  "meta_tag": "e9d4f9cdf43402ecbedb6242860a36bf64c10f14",
  "no_download": null,
  "on_recent_list": true,
  "org": 8,
  "original_file": "Shmuel__Zucker__05_03_2023__e9d4f9cdf43402ecbedb6242860a36bf64c10f14.mp4",
  "phone_system_short_extension": "336184",
  "private": false,
  "private_code": null,
  "published_by": 39,
  "published_by_name": "hatzolahq79@gmail.com",
  "slug": "lag-bomer-finding-the-godliness-in-the-evil",
  "speaker": 539,
  "subcategory": 39,
  "text": null,
  "thumbnail": "1665056450-5d75891b7e275dd3423552f8b40b5a29724f4614d01cd7f4635184b4865d36ad-d",
  "thumbnail_url": "https://ta-lectures.s3.us-east-005.backblazeb2.com/thumbnails/236358/236358.jpg",
  "title": "Lag B'Omer: Finding the Godliness in the Evil",
  "title_rtl": false,
  "desc": null,
  "video_download_size_string": "58.41MB",
  "video_download_size": 61249315,
  "vimeo_video": "vimeo_002---/videos/823593575",
  "vimeo_video_links": [
    "https://proxier.torahanytime.com/aHR0cHM6Ly90YS1sZWN0dXJlcy5zMy51cy1lYXN0LTAwNS5iYWNrYmxhemViMi5jb20vbXA0LzIzNjM1OC5tcDQ/bb1c6e5c3c0810cf7856ba591b76d876a447adade5615332104753b18801f318.mp4?has_women=0&speaker_id=539&digest=881d2d4f0085076d0c67e2e1187f4e1171cab68ca9bbafb35b751b0da15106fe"
  ],
  "vimeo_video_links_legacy": [
    "https://player.vimeo.com/progressive_redirect/playback/823593575/rendition/360p/file.mp4?loc=external&oauth2_token_id=1080790441&signature=6c93c15b9fd3d6374e591fa3c768a02bbebcc9e9d6e084bb11c7c149f826d883",
    "https://player.vimeo.com/external/823593575.m3u8?s=5da0fbd807b8208271b51d60cfda595c5d889b69&oauth2_token_id=1080790441"
  ],
  "vimeo_hash": "21e4a09462",
  "box_id": 1205867472013,
  "publish_by_date": null,
  "date_to_show": "2023-05-04T03:30:42.000Z",
  "is_only_watchable_by_female": false,
  "is_only_listenable_by_female": false,
  "is_only_discoverable_by_female": false,
  "is_only_discoverable_within_org": false,
  "is_not_discoverable": false,
  "m3u8_url": null,
  "mp4_url": "https://ta-lectures.s3.us-east-005.backblazeb2.com/mp4/236358.mp4",
  "mp3_url": "https://dl.torahanytime.com/mp3/236358--____04_04_2023__7bfd8ea5-650b-4517-951d-8d50c0d171a2.mp4.mp3",
  "watermarked_original_mp4_url": null,
  "ragie_document_id": "8256fea7-1b60-4493-956b-0defbca01162",
  "created_at": "2023-05-04T03:30:42.000Z",
  "updated_at": "2025-04-30T04:21:43.000Z",
  "deleted_at": null,
  "subcategories": [
    {
      "id": 39,
      "name": "Lag B'Omer",
      "english_name": "Lag B’Omer"
    }
  ],
  "parent_info": null,
  "projects": [
    {
      "id": 1,
      "name": "TorahAnytime"
    }
  ],
  "categories": [
    {
      "id": 8,
      "name": "Holidays",
      "english_name": "Holidays"
    }
  ],
  "language_name": "English",
  "speaker_name_first": "Shmuel",
  "speaker_name_last": "Zucker",
  "speaker_photo": "r-shmuel-zucker_photo_16b3ed4da888e4d100d8d5f0b4e41c0e",
  "female": false,
  "view_female_level": 0,
  "speaker_no_download": 0,
  "speaker_title": "Rabbi",
  "speaker_title_short": "R'",
  "video_url": "https://ta-lectures.s3.us-east-005.backblazeb2.com/mp4/236358.mp4",
  "audio_url": "https://dl.torahanytime.com/mp3/236358--____04_04_2023__7bfd8ea5-650b-4517-951d-8d50c0d171a2.mp4.mp3",
  "vimeo_video_id": "823593575",
  "proxy_mp4_url": "https://proxier.torahanytime.com/aHR0cHM6Ly90YS1sZWN0dXJlcy5zMy51cy1lYXN0LTAwNS5iYWNrYmxhemViMi5jb20vbXA0LzIzNjM1OC5tcDQ/bb1c6e5c3c0810cf7856ba591b76d876a447adade5615332104753b18801f318.mp4?has_women=0&speaker_id=539&digest=881d2d4f0085076d0c67e2e1187f4e1171cab68ca9bbafb35b751b0da15106fe",
  "likeCount": 2,
  "viewCount": 817
}