{
  "date_created": "2025-01-24T03:40:06.000Z",
  "audio_download_size_string": "3.9 MiB",
  "audio_download_size": 4106873,
  "auto_display": false,
  "bitly_audio": "https://mytat.me/a346321",
  "bitly_video": null,
  "category": 23,
  "clip_link": null,
  "clip_parent": null,
  "clip_title": null,
  "clipper_email": null,
  "date_recorded": "2025-01-24",
  "dedication": null,
  "display_active": true,
  "duration": 666,
  "event_speakers": null,
  "host": 0,
  "id": 346321,
  "id_md5": null,
  "is_clip": null,
  "is_short": false,
  "jwplayer_mediaId": "t4AeTS3v",
  "ladies": false,
  "language": 1,
  "lecture_url": null,
  "location": 0,
  "media": "346321--____00_05_2025__d47909f4-2955-43bb-9f8b-7099e27c7eed.mp3.mp3.mp4",
  "meta_tag": "05d1bbf013231299de8455fb04f3a016c84ecc59",
  "no_download": null,
  "on_recent_list": true,
  "org": 0,
  "original_file": null,
  "phone_system_short_extension": "446234",
  "private": false,
  "private_code": null,
  "published_by": 98686,
  "published_by_name": "Dov Tepler",
  "slug": "parshat-vaeira-some-lessons-from-the-parsha",
  "speaker": 1306,
  "subcategory": 58,
  "text": null,
  "thumbnail": "1246599496-3101ff087fb6c15908efd6b0b55a02014d7a19ffa54266fb79c2b45cc3169c5f-d",
  "thumbnail_url": "https://ta-lectures.s3.us-east-005.backblazeb2.com/thumbnails/audio.jpg",
  "title": "Parshat Va'eira: Some lessons from the Parsha",
  "title_rtl": false,
  "desc": null,
  "video_download_size_string": null,
  "video_download_size": null,
  "vimeo_video": null,
  "vimeo_video_links": null,
  "vimeo_video_links_legacy": null,
  "vimeo_hash": null,
  "box_id": 1758045037990,
  "publish_by_date": null,
  "date_to_show": "2025-01-24T03:40:06.000Z",
  "is_only_watchable_by_female": false,
  "is_only_listenable_by_female": false,
  "is_only_discoverable_by_female": false,
  "is_only_discoverable_within_org": false,
  "is_not_discoverable": false,
  "m3u8_url": null,
  "mp4_url": null,
  "mp3_url": "https://dl.torahanytime.com/mp3/346321--____00_05_2025__d47909f4-2955-43bb-9f8b-7099e27c7eed.mp3",
  "watermarked_original_mp4_url": null,
  "ragie_document_id": "e117875f-47a7-4a0e-930d-4a6c7ddc9a8e",
  "created_at": "2025-01-24T03:40:06.000Z",
  "updated_at": "2025-03-06T14:29:45.000Z",
  "deleted_at": null,
  "subcategories": [
    {
      "id": 58,
      "name": "Va'eira",
      "english_name": null
    }
  ],
  "parent_info": null,
  "projects": [
    {
      "id": 1,
      "name": "TorahAnytime"
    }
  ],
  "categories": [
    {
      "id": 23,
      "name": "Parasha/Torah Portion",
      "english_name": "Torah"
    }
  ],
  "language_name": "English",
  "speaker_name_first": "Dov",
  "speaker_name_last": "Tepler",
  "speaker_photo": "r-dov-tepler_photo_f43f0d71cd7ce911f60b3a44e9cdc63f",
  "female": false,
  "view_female_level": 0,
  "speaker_no_download": 0,
  "speaker_title": "Rabbi",
  "speaker_title_short": "R'",
  "audio_url": "https://dl.torahanytime.com/mp3/346321--____00_05_2025__d47909f4-2955-43bb-9f8b-7099e27c7eed.mp3",
  "likeCount": 0,
  "viewCount": 118
}