{
  "date_created": "2025-05-15T14:19:51.000Z",
  "audio_download_size_string": null,
  "audio_download_size": null,
  "auto_display": false,
  "bitly_audio": "https://mytat.me/a369358",
  "bitly_video": "https://mytat.me/v369358",
  "category": 18,
  "clip_link": null,
  "clip_parent": null,
  "clip_title": null,
  "clipper_email": null,
  "date_recorded": "2025-05-15",
  "dedication": null,
  "display_active": true,
  "duration": 3510,
  "event_speakers": null,
  "host": 0,
  "id": 369358,
  "id_md5": null,
  "is_clip": null,
  "is_short": false,
  "jwplayer_mediaId": null,
  "ladies": false,
  "language": 1,
  "lecture_url": null,
  "location": 0,
  "media": "",
  "meta_tag": "6b8c398e72c424dfcf8dbf72f17ded56c1bc4217",
  "no_download": null,
  "on_recent_list": true,
  "org": 0,
  "original_file": null,
  "phone_system_short_extension": "469100",
  "private": false,
  "private_code": null,
  "published_by": 67205,
  "published_by_name": "joshua stern",
  "slug": "shavuot-daf-14",
  "speaker": 587,
  "subcategory": 100029,
  "text": null,
  "thumbnail": "2016151305-d3746d2618597c555544d987e877b06cd641f13685b5c9ab01d2fc7e19068755-d?region=us",
  "thumbnail_url": "https://ta-lectures.s3.us-east-005.backblazeb2.com/thumbnails/369358/369358-swb8ef.jpg",
  "title": "Shavuot Daf 14",
  "title_rtl": false,
  "desc": null,
  "video_download_size_string": null,
  "video_download_size": null,
  "vimeo_video": null,
  "vimeo_video_links": [
    "https://proxier.torahanytime.com/aHR0cHM6Ly90YS1sZWN0dXJlcy5zMy51cy1lYXN0LTAwNS5iYWNrYmxhemViMi5jb20vaGxzLzM2OTM1OC9zd2IzdGIvbWFzdGVyLm0zdTg/0bcf9e7bc3acdcd4d54e3dcf594de5f3a55330c5825f238b383dfa66c2b19c1f.m3u8?has_women=0&speaker_id=587&digest=5c131cacb65de8c5fba2fd6eead0e2bdbc8daef39b312b658c730c14ebe7376d",
    "https://proxier.torahanytime.com/aHR0cHM6Ly90YS1sZWN0dXJlcy5zMy51cy1lYXN0LTAwNS5iYWNrYmxhemViMi5jb20vbXA0LzM2OTM1OC1zd2IzdGIubXA0/36e65e6241ab25c74f2dbd1c46b6fa8b9c5020c86dd4791293d61c7f7c770e92.mp4?has_women=0&speaker_id=587&digest=5c131cacb65de8c5fba2fd6eead0e2bdbc8daef39b312b658c730c14ebe7376d"
  ],
  "vimeo_video_links_legacy": true,
  "vimeo_hash": null,
  "box_id": null,
  "publish_by_date": null,
  "date_to_show": "2025-05-15T15:59:07.000Z",
  "is_only_watchable_by_female": false,
  "is_only_listenable_by_female": false,
  "is_only_discoverable_by_female": false,
  "is_only_discoverable_within_org": false,
  "is_not_discoverable": false,
  "m3u8_url": "https://ta-lectures.s3.us-east-005.backblazeb2.com/hls/369358/swb3tb/master.m3u8",
  "mp4_url": "https://ta-lectures.s3.us-east-005.backblazeb2.com/mp4/369358-swb3tb.mp4",
  "mp3_url": "https://ta-lectures.s3.us-east-005.backblazeb2.com/mp3/369358/369358-swb3tb.mp3",
  "watermarked_original_mp4_url": null,
  "ragie_document_id": "dc2d1a3c-56a1-4836-a464-a9f1f77d3d2c",
  "created_at": "2025-05-15T14:19:51.000Z",
  "updated_at": "2025-05-15T15:59:07.000Z",
  "deleted_at": null,
  "subcategories": [
    {
      "id": 100029,
      "name": "Shavuot",
      "english_name": null
    }
  ],
  "parent_info": null,
  "projects": [
    {
      "id": 1,
      "name": "TorahAnytime"
    }
  ],
  "categories": [
    {
      "id": 18,
      "name": "Daf Yomi/Daily Talmud",
      "english_name": "Talmud"
    }
  ],
  "language_name": "English",
  "speaker_name_first": "Shea",
  "speaker_name_last": "Stern",
  "speaker_photo": "",
  "female": false,
  "view_female_level": 0,
  "speaker_no_download": 0,
  "speaker_title": "Rabbi",
  "speaker_title_short": "R'",
  "video_url": "https://ta-lectures.s3.us-east-005.backblazeb2.com/mp4/369358-swb3tb.mp4",
  "audio_url": "https://ta-lectures.s3.us-east-005.backblazeb2.com/mp3/369358/369358-swb3tb.mp3",
  "proxy_m3u8_url": "https://proxier.torahanytime.com/aHR0cHM6Ly90YS1sZWN0dXJlcy5zMy51cy1lYXN0LTAwNS5iYWNrYmxhemViMi5jb20vaGxzLzM2OTM1OC9zd2IzdGIvbWFzdGVyLm0zdTg/0bcf9e7bc3acdcd4d54e3dcf594de5f3a55330c5825f238b383dfa66c2b19c1f.m3u8?has_women=0&speaker_id=587&digest=5c131cacb65de8c5fba2fd6eead0e2bdbc8daef39b312b658c730c14ebe7376d",
  "vimeo_proxy_m3u8_url": "https://proxier.torahanytime.com/aHR0cHM6Ly90YS1sZWN0dXJlcy5zMy51cy1lYXN0LTAwNS5iYWNrYmxhemViMi5jb20vaGxzLzM2OTM1OC9zd2IzdGIvbWFzdGVyLm0zdTg/0bcf9e7bc3acdcd4d54e3dcf594de5f3a55330c5825f238b383dfa66c2b19c1f.m3u8?has_women=0&speaker_id=587&digest=5c131cacb65de8c5fba2fd6eead0e2bdbc8daef39b312b658c730c14ebe7376d",
  "proxy_mp4_url": "https://proxier.torahanytime.com/aHR0cHM6Ly90YS1sZWN0dXJlcy5zMy51cy1lYXN0LTAwNS5iYWNrYmxhemViMi5jb20vbXA0LzM2OTM1OC1zd2IzdGIubXA0/36e65e6241ab25c74f2dbd1c46b6fa8b9c5020c86dd4791293d61c7f7c770e92.mp4?has_women=0&speaker_id=587&digest=5c131cacb65de8c5fba2fd6eead0e2bdbc8daef39b312b658c730c14ebe7376d",
  "likeCount": 0,
  "viewCount": 32
}