{
  "date_created": "2025-06-24T05:37:29.000Z",
  "audio_download_size_string": null,
  "audio_download_size": null,
  "auto_display": false,
  "bitly_audio": "https://mytat.me/a377230",
  "bitly_video": null,
  "category": 253,
  "clip_link": null,
  "clip_parent": null,
  "clip_title": null,
  "clipper_email": null,
  "date_recorded": "2025-06-24",
  "dedication": null,
  "display_active": true,
  "duration": 2412,
  "event_speakers": null,
  "host": 0,
  "id": 377230,
  "id_md5": null,
  "is_clip": null,
  "is_short": false,
  "jwplayer_mediaId": null,
  "ladies": false,
  "language": 1,
  "lecture_url": null,
  "location": 0,
  "media": "",
  "meta_tag": "54ef648f4384ef880564c8897c1908c018b5f65d",
  "no_download": null,
  "on_recent_list": true,
  "org": 0,
  "original_file": null,
  "phone_system_short_extension": "477179",
  "private": false,
  "private_code": null,
  "published_by": 51603,
  "published_by_name": "Yonason Roodyn",
  "slug": "the-hidden-strength-within-building-bitachon-in-turbulent-times",
  "speaker": 162,
  "subcategory": 0,
  "text": null,
  "thumbnail": "",
  "thumbnail_url": null,
  "title": "The Hidden Strength Within: Building Bitachon In Turbulent Times. ",
  "title_rtl": false,
  "desc": null,
  "video_download_size_string": null,
  "video_download_size": null,
  "vimeo_video": null,
  "vimeo_video_links": null,
  "vimeo_video_links_legacy": true,
  "vimeo_hash": null,
  "box_id": null,
  "publish_by_date": null,
  "date_to_show": "2025-06-24T05:38:06.000Z",
  "is_only_watchable_by_female": false,
  "is_only_listenable_by_female": false,
  "is_only_discoverable_by_female": false,
  "is_only_discoverable_within_org": false,
  "is_not_discoverable": false,
  "m3u8_url": null,
  "mp4_url": null,
  "mp3_url": "https://ta-lectures.s3.us-east-005.backblazeb2.com/mp3/377230/377230-syciap.mp3",
  "watermarked_original_mp4_url": null,
  "ragie_document_id": "5cafb20a-90a9-4fa6-94e1-debe8540a623",
  "created_at": "2025-06-24T05:37:29.000Z",
  "updated_at": "2025-06-24T05:38:14.000Z",
  "deleted_at": null,
  "subcategories": [],
  "parent_info": null,
  "projects": [
    {
      "id": 1,
      "name": "TorahAnytime"
    }
  ],
  "categories": [
    {
      "id": 253,
      "name": "Response to Tragic Events",
      "english_name": "Tragic Events"
    }
  ],
  "language_name": "English",
  "speaker_name_first": "Yonoson",
  "speaker_name_last": "Roodyn",
  "speaker_photo": "r-yonoson-roodyn_photo_43a186ab1a1cd1afd815da6c1b0b9ece",
  "female": false,
  "view_female_level": 0,
  "speaker_no_download": 0,
  "speaker_title": "Rabbi",
  "speaker_title_short": "R'",
  "audio_url": "https://ta-lectures.s3.us-east-005.backblazeb2.com/mp3/377230/377230-syciap.mp3",
  "likeCount": 0,
  "viewCount": 329
}