{
  "date_created": "2025-07-10T11:01:29.000Z",
  "audio_download_size_string": null,
  "audio_download_size": null,
  "auto_display": false,
  "bitly_audio": "https://mytat.me/a380543",
  "bitly_video": "https://mytat.me/v380543",
  "category": 23,
  "clip_link": null,
  "clip_parent": null,
  "clip_title": null,
  "clipper_email": null,
  "date_recorded": "2025-07-10",
  "dedication": null,
  "display_active": true,
  "duration": 700,
  "event_speakers": null,
  "host": 0,
  "id": 380543,
  "id_md5": null,
  "is_clip": null,
  "is_short": false,
  "jwplayer_mediaId": null,
  "ladies": false,
  "language": 1,
  "lecture_url": null,
  "location": 0,
  "media": "",
  "meta_tag": "df59be5d73fb3077f795d9057680f4ad0d31039b",
  "no_download": null,
  "on_recent_list": true,
  "org": 0,
  "original_file": null,
  "phone_system_short_extension": "480424",
  "private": false,
  "private_code": null,
  "published_by": 129051,
  "published_by_name": "meir b. Kahane",
  "slug": "aish-kodesh-balak-5700-i-am-bigger-than-what-i-am-going-through-202122-series-enhanced-iii",
  "speaker": 1091,
  "subcategory": 84,
  "text": null,
  "thumbnail": "2035429336-7534b7ff2fba676e23cb2b9243920f726368482b45ea3d53c0532d9faccbf312-d?region=us",
  "thumbnail_url": "https://ta-lectures.s3.us-east-005.backblazeb2.com/thumbnails/380543/380543-sz6kb2.jpg",
  "title": "Aish Kodesh- Balak, 5700, I Am Bigger Than What I Am Going Through (2021/22 Series- Enhanced III)",
  "title_rtl": false,
  "desc": null,
  "video_download_size_string": null,
  "video_download_size": null,
  "vimeo_video": null,
  "vimeo_video_links": [
    "https://proxier.torahanytime.com/aHR0cHM6Ly90YS1sZWN0dXJlcy5zMy51cy1lYXN0LTAwNS5iYWNrYmxhemViMi5jb20vaGxzLzM4MDU0My9zejZqeW8vbWFzdGVyLm0zdTg/01deff8b433f83eaac2b5996fa026e9dc58c5ef3eb526ec939929b7ad6ab86a7.m3u8?has_women=0&speaker_id=1091&digest=2f922e228c82cf8c0672fa59c28b2c298de5400a54b0c7c673e03edcedb1a150",
    "https://proxier.torahanytime.com/aHR0cHM6Ly90YS1sZWN0dXJlcy5zMy51cy1lYXN0LTAwNS5iYWNrYmxhemViMi5jb20vbXA0LzM4MDU0My1zejZqeW8ubXA0/00360d1041dd491c2050e6bcba9919775cd0f03785784bf4270abeab19d0218a.mp4?has_women=0&speaker_id=1091&digest=2f922e228c82cf8c0672fa59c28b2c298de5400a54b0c7c673e03edcedb1a150"
  ],
  "vimeo_video_links_legacy": true,
  "vimeo_hash": null,
  "box_id": 1920367388569,
  "publish_by_date": null,
  "date_to_show": "2025-07-10T11:09:05.000Z",
  "is_only_watchable_by_female": false,
  "is_only_listenable_by_female": false,
  "is_only_discoverable_by_female": false,
  "is_only_discoverable_within_org": false,
  "is_not_discoverable": false,
  "m3u8_url": "https://ta-lectures.s3.us-east-005.backblazeb2.com/hls/380543/sz6jyo/master.m3u8",
  "mp4_url": "https://ta-lectures.s3.us-east-005.backblazeb2.com/mp4/380543-sz6jyo.mp4",
  "mp3_url": "https://ta-lectures.s3.us-east-005.backblazeb2.com/mp3/380543/380543-sz6jyo.mp3",
  "watermarked_original_mp4_url": null,
  "ragie_document_id": "5925b9bc-57a4-4297-a2a3-d0ac36a21827",
  "created_at": "2025-07-10T11:01:29.000Z",
  "updated_at": "2025-07-10T12:21:33.000Z",
  "deleted_at": null,
  "subcategories": [
    {
      "id": 84,
      "name": "Balak",
      "english_name": null
    }
  ],
  "parent_info": null,
  "projects": [
    {
      "id": 1,
      "name": "TorahAnytime"
    }
  ],
  "categories": [
    {
      "id": 23,
      "name": "Parasha/Torah Portion",
      "english_name": "Torah"
    }
  ],
  "language_name": "English",
  "speaker_name_first": "Meir",
  "speaker_name_last": "Kahane",
  "speaker_photo": "r-meir-kahane_photo",
  "female": false,
  "view_female_level": 0,
  "speaker_no_download": 0,
  "speaker_title": "Rabbi",
  "speaker_title_short": "R'",
  "video_url": "https://ta-lectures.s3.us-east-005.backblazeb2.com/mp4/380543-sz6jyo.mp4",
  "audio_url": "https://ta-lectures.s3.us-east-005.backblazeb2.com/mp3/380543/380543-sz6jyo.mp3",
  "proxy_m3u8_url": "https://proxier.torahanytime.com/aHR0cHM6Ly90YS1sZWN0dXJlcy5zMy51cy1lYXN0LTAwNS5iYWNrYmxhemViMi5jb20vaGxzLzM4MDU0My9zejZqeW8vbWFzdGVyLm0zdTg/01deff8b433f83eaac2b5996fa026e9dc58c5ef3eb526ec939929b7ad6ab86a7.m3u8?has_women=0&speaker_id=1091&digest=2f922e228c82cf8c0672fa59c28b2c298de5400a54b0c7c673e03edcedb1a150",
  "vimeo_proxy_m3u8_url": "https://proxier.torahanytime.com/aHR0cHM6Ly90YS1sZWN0dXJlcy5zMy51cy1lYXN0LTAwNS5iYWNrYmxhemViMi5jb20vaGxzLzM4MDU0My9zejZqeW8vbWFzdGVyLm0zdTg/01deff8b433f83eaac2b5996fa026e9dc58c5ef3eb526ec939929b7ad6ab86a7.m3u8?has_women=0&speaker_id=1091&digest=2f922e228c82cf8c0672fa59c28b2c298de5400a54b0c7c673e03edcedb1a150",
  "proxy_mp4_url": "https://proxier.torahanytime.com/aHR0cHM6Ly90YS1sZWN0dXJlcy5zMy51cy1lYXN0LTAwNS5iYWNrYmxhemViMi5jb20vbXA0LzM4MDU0My1zejZqeW8ubXA0/00360d1041dd491c2050e6bcba9919775cd0f03785784bf4270abeab19d0218a.mp4?has_women=0&speaker_id=1091&digest=2f922e228c82cf8c0672fa59c28b2c298de5400a54b0c7c673e03edcedb1a150",
  "likeCount": 2,
  "viewCount": 2
}