{
  "date_created": "2025-08-29T12:53:30.000Z",
  "audio_download_size_string": null,
  "audio_download_size": null,
  "auto_display": false,
  "bitly_audio": "https://mytat.me/a390579",
  "bitly_video": "https://mytat.me/v390579",
  "category": 23,
  "clip_link": null,
  "clip_parent": null,
  "clip_title": null,
  "clipper_email": null,
  "date_recorded": "2025-08-29",
  "dedication": null,
  "display_active": true,
  "duration": 535,
  "event_speakers": null,
  "host": 0,
  "id": 390579,
  "id_md5": null,
  "is_clip": null,
  "is_short": false,
  "jwplayer_mediaId": null,
  "ladies": false,
  "language": 1,
  "lecture_url": null,
  "location": 0,
  "media": "",
  "meta_tag": "28c70959a3c40e4e23b64d54a69a10dacfe43c13",
  "no_download": null,
  "on_recent_list": true,
  "org": 0,
  "original_file": null,
  "phone_system_short_extension": "490578",
  "private": false,
  "private_code": null,
  "published_by": 53431,
  "published_by_name": "Nachman Meisels",
  "slug": "if-the-עדים-are-כהנים-or-נזירים-so-how-can-they-carry-out-שריפה-or-חנק-as-they-will-become-טמא-when-he-dies-will-he-be-פטור-like-by-נקטעה-יד-העדים",
  "speaker": 1402,
  "subcategory": 92,
  "text": null,
  "thumbnail": "2052928292-c0917ddd1b36fa5bb46e2bb4b70e36b9035deb9e07780c62e18d84d5f5f847b6-d?region=us",
  "thumbnail_url": "https://ta-lectures.s3.us-east-005.backblazeb2.com/thumbnails/390579/390579-t1ramk.jpg",
  "title": "If the עדים are כהנים or נזירים, so how can they carry out שריפה or חנק as they will become טמא when he dies ? Will he be פטור like by נקטעה יד העדים?",
  "title_rtl": false,
  "desc": null,
  "video_download_size_string": null,
  "video_download_size": null,
  "vimeo_video": null,
  "vimeo_video_links": [
    "https://proxier.torahanytime.com/aHR0cHM6Ly90YS1sZWN0dXJlcy5zMy51cy1lYXN0LTAwNS5iYWNrYmxhemViMi5jb20vaGxzLzM5MDU3OS90MXJhaGsvbWFzdGVyLm0zdTg/400a0374a0f2a04c51f4d9a9b20224b1c241d41734daf49d2c40bfd855af9d85.m3u8?has_women=0&speaker_id=1402&digest=7aad55c73544577b0597b7ac20a7d868f51052c3ff1d0512b81de4dd7dc7fe7b",
    "https://proxier.torahanytime.com/aHR0cHM6Ly90YS1sZWN0dXJlcy5zMy51cy1lYXN0LTAwNS5iYWNrYmxhemViMi5jb20vbXA0LzM5MDU3OS10MXJhaGsubXA0/259942d597bef416317659446c47b58449c34f987d61a2f4f8fc0242e35f6c61.mp4?has_women=0&speaker_id=1402&digest=7aad55c73544577b0597b7ac20a7d868f51052c3ff1d0512b81de4dd7dc7fe7b"
  ],
  "vimeo_video_links_legacy": true,
  "vimeo_hash": null,
  "box_id": 1969611657121,
  "publish_by_date": null,
  "date_to_show": "2025-08-29T12:56:46.000Z",
  "is_only_watchable_by_female": false,
  "is_only_listenable_by_female": false,
  "is_only_discoverable_by_female": false,
  "is_only_discoverable_within_org": false,
  "is_not_discoverable": false,
  "m3u8_url": "https://ta-lectures.s3.us-east-005.backblazeb2.com/hls/390579/t1rahk/master.m3u8",
  "mp4_url": "https://ta-lectures.s3.us-east-005.backblazeb2.com/mp4/390579-t1rahk.mp4",
  "mp3_url": "https://ta-lectures.s3.us-east-005.backblazeb2.com/mp3/390579/390579-t1rahk.mp3",
  "watermarked_original_mp4_url": null,
  "ragie_document_id": "e2d8848c-fb37-428d-8b27-ae229db39973",
  "created_at": "2025-08-29T12:53:30.000Z",
  "updated_at": "2025-08-29T16:48:55.000Z",
  "deleted_at": null,
  "subcategories": [
    {
      "id": 92,
      "name": "Shoftim",
      "english_name": null
    }
  ],
  "parent_info": null,
  "projects": [
    {
      "id": 1,
      "name": "TorahAnytime"
    }
  ],
  "categories": [
    {
      "id": 23,
      "name": "Parasha/Torah Portion",
      "english_name": "Torah"
    }
  ],
  "language_name": "English",
  "speaker_name_first": "Eli",
  "speaker_name_last": "Garfinkel",
  "speaker_photo": "r-eli-garfinkel_photo_053ba9ca37441cc52be2d3bed5867e5f",
  "female": false,
  "view_female_level": 0,
  "speaker_no_download": 0,
  "speaker_title": "Rabbi",
  "speaker_title_short": "R'",
  "video_url": "https://ta-lectures.s3.us-east-005.backblazeb2.com/mp4/390579-t1rahk.mp4",
  "audio_url": "https://ta-lectures.s3.us-east-005.backblazeb2.com/mp3/390579/390579-t1rahk.mp3",
  "proxy_m3u8_url": "https://proxier.torahanytime.com/aHR0cHM6Ly90YS1sZWN0dXJlcy5zMy51cy1lYXN0LTAwNS5iYWNrYmxhemViMi5jb20vaGxzLzM5MDU3OS90MXJhaGsvbWFzdGVyLm0zdTg/400a0374a0f2a04c51f4d9a9b20224b1c241d41734daf49d2c40bfd855af9d85.m3u8?has_women=0&speaker_id=1402&digest=7aad55c73544577b0597b7ac20a7d868f51052c3ff1d0512b81de4dd7dc7fe7b",
  "vimeo_proxy_m3u8_url": "https://proxier.torahanytime.com/aHR0cHM6Ly90YS1sZWN0dXJlcy5zMy51cy1lYXN0LTAwNS5iYWNrYmxhemViMi5jb20vaGxzLzM5MDU3OS90MXJhaGsvbWFzdGVyLm0zdTg/400a0374a0f2a04c51f4d9a9b20224b1c241d41734daf49d2c40bfd855af9d85.m3u8?has_women=0&speaker_id=1402&digest=7aad55c73544577b0597b7ac20a7d868f51052c3ff1d0512b81de4dd7dc7fe7b",
  "proxy_mp4_url": "https://proxier.torahanytime.com/aHR0cHM6Ly90YS1sZWN0dXJlcy5zMy51cy1lYXN0LTAwNS5iYWNrYmxhemViMi5jb20vbXA0LzM5MDU3OS10MXJhaGsubXA0/259942d597bef416317659446c47b58449c34f987d61a2f4f8fc0242e35f6c61.mp4?has_women=0&speaker_id=1402&digest=7aad55c73544577b0597b7ac20a7d868f51052c3ff1d0512b81de4dd7dc7fe7b",
  "likeCount": 0,
  "viewCount": 35
}