{
  "date_created": "2025-09-01T01:02:01.000Z",
  "audio_download_size_string": null,
  "audio_download_size": null,
  "auto_display": false,
  "bitly_audio": "https://mytat.me/a390887",
  "bitly_video": "https://mytat.me/v390887",
  "category": 209,
  "clip_link": null,
  "clip_parent": null,
  "clip_title": null,
  "clipper_email": null,
  "date_recorded": "2025-09-01",
  "dedication": null,
  "display_active": true,
  "duration": 65,
  "event_speakers": null,
  "host": 0,
  "id": 390887,
  "id_md5": null,
  "is_clip": null,
  "is_short": false,
  "jwplayer_mediaId": null,
  "ladies": false,
  "language": 1,
  "lecture_url": null,
  "location": 0,
  "media": "",
  "meta_tag": "a094198a1139b068561fb383b094a8b660f88d1f",
  "no_download": null,
  "on_recent_list": true,
  "org": 0,
  "original_file": null,
  "phone_system_short_extension": "490886",
  "private": false,
  "private_code": null,
  "published_by": 216430,
  "published_by_name": "Moshe Dov_Heber2",
  "slug": "sparks-of-wisdom-17-patience",
  "speaker": 1477,
  "subcategory": 0,
  "text": null,
  "thumbnail": "2053593244-3a0a17d8fe4b7f5e6afb35200ac38282fdb9ffb0fdc763629e37dc3ebeaa7aec-d?region=us",
  "thumbnail_url": "https://ta-lectures.s3.us-east-005.backblazeb2.com/thumbnails/390887/390887-t1vxje.jpg",
  "title": "Sparks of Wisdom #17- Patience! ",
  "title_rtl": false,
  "desc": null,
  "video_download_size_string": null,
  "video_download_size": null,
  "vimeo_video": null,
  "vimeo_video_links": [
    "https://proxier.torahanytime.com/aHR0cHM6Ly90YS1sZWN0dXJlcy5zMy51cy1lYXN0LTAwNS5iYWNrYmxhemViMi5jb20vaGxzLzM5MDg4Ny90MXZ4amwvbWFzdGVyLm0zdTg/7e5803ee2fbf9f2b90b71c02938969decb7258d748360e4700360b998e35f4c7.m3u8?has_women=0&speaker_id=1477&digest=2b3926d59bd19456abeb06836726a907e6208972af08e67bf5cc9939caf7668b",
    "https://proxier.torahanytime.com/aHR0cHM6Ly90YS1sZWN0dXJlcy5zMy51cy1lYXN0LTAwNS5iYWNrYmxhemViMi5jb20vbXA0LzM5MDg4Ny10MXZ4amwubXA0/3036287c72dfa910dabcc629753dd1827250749ff73fc1d2114b2a1b75315d24.mp4?has_women=0&speaker_id=1477&digest=2b3926d59bd19456abeb06836726a907e6208972af08e67bf5cc9939caf7668b"
  ],
  "vimeo_video_links_legacy": true,
  "vimeo_hash": null,
  "box_id": 1971430542099,
  "publish_by_date": "2025-09-03T12:58:00.000Z",
  "date_to_show": "2025-09-03T12:58:00.000Z",
  "is_only_watchable_by_female": false,
  "is_only_listenable_by_female": false,
  "is_only_discoverable_by_female": false,
  "is_only_discoverable_within_org": false,
  "is_not_discoverable": false,
  "m3u8_url": "https://ta-lectures.s3.us-east-005.backblazeb2.com/hls/390887/t1vxjl/master.m3u8",
  "mp4_url": "https://ta-lectures.s3.us-east-005.backblazeb2.com/mp4/390887-t1vxjl.mp4",
  "mp3_url": "https://ta-lectures.s3.us-east-005.backblazeb2.com/mp3/390887/390887-t1vxjl.mp3",
  "watermarked_original_mp4_url": null,
  "ragie_document_id": "0a9f49c3-7e5f-426c-bb48-b58115d71f70",
  "created_at": "2025-09-01T01:02:01.000Z",
  "updated_at": "2025-09-03T12:58:00.000Z",
  "deleted_at": null,
  "subcategories": [],
  "parent_info": null,
  "projects": [
    {
      "id": 1,
      "name": "TorahAnytime"
    }
  ],
  "categories": [
    {
      "id": 209,
      "name": "StoryAnytime Kids",
      "english_name": null
    }
  ],
  "language_name": "English",
  "speaker_name_first": "Moshe Dov",
  "speaker_name_last": "Heber",
  "speaker_photo": "r-moshe-dov-heber_photo_df679b0e6da0186ed43f7a8e191a7498",
  "female": false,
  "view_female_level": 0,
  "speaker_no_download": 0,
  "speaker_title": "Rabbi",
  "speaker_title_short": "R'",
  "video_url": "https://ta-lectures.s3.us-east-005.backblazeb2.com/mp4/390887-t1vxjl.mp4",
  "audio_url": "https://ta-lectures.s3.us-east-005.backblazeb2.com/mp3/390887/390887-t1vxjl.mp3",
  "proxy_m3u8_url": "https://proxier.torahanytime.com/aHR0cHM6Ly90YS1sZWN0dXJlcy5zMy51cy1lYXN0LTAwNS5iYWNrYmxhemViMi5jb20vaGxzLzM5MDg4Ny90MXZ4amwvbWFzdGVyLm0zdTg/7e5803ee2fbf9f2b90b71c02938969decb7258d748360e4700360b998e35f4c7.m3u8?has_women=0&speaker_id=1477&digest=2b3926d59bd19456abeb06836726a907e6208972af08e67bf5cc9939caf7668b",
  "vimeo_proxy_m3u8_url": "https://proxier.torahanytime.com/aHR0cHM6Ly90YS1sZWN0dXJlcy5zMy51cy1lYXN0LTAwNS5iYWNrYmxhemViMi5jb20vaGxzLzM5MDg4Ny90MXZ4amwvbWFzdGVyLm0zdTg/7e5803ee2fbf9f2b90b71c02938969decb7258d748360e4700360b998e35f4c7.m3u8?has_women=0&speaker_id=1477&digest=2b3926d59bd19456abeb06836726a907e6208972af08e67bf5cc9939caf7668b",
  "proxy_mp4_url": "https://proxier.torahanytime.com/aHR0cHM6Ly90YS1sZWN0dXJlcy5zMy51cy1lYXN0LTAwNS5iYWNrYmxhemViMi5jb20vbXA0LzM5MDg4Ny10MXZ4amwubXA0/3036287c72dfa910dabcc629753dd1827250749ff73fc1d2114b2a1b75315d24.mp4?has_women=0&speaker_id=1477&digest=2b3926d59bd19456abeb06836726a907e6208972af08e67bf5cc9939caf7668b",
  "likeCount": 0,
  "viewCount": 2
}