{
  "date_created": "2025-09-03T14:16:23.000Z",
  "audio_download_size_string": null,
  "audio_download_size": null,
  "auto_display": false,
  "bitly_audio": "https://mytat.me/a391518",
  "bitly_video": "https://mytat.me/v391518",
  "category": 18,
  "clip_link": null,
  "clip_parent": null,
  "clip_title": null,
  "clipper_email": null,
  "date_recorded": "2025-09-03",
  "dedication": null,
  "display_active": true,
  "duration": 3504,
  "event_speakers": null,
  "host": 0,
  "id": 391518,
  "id_md5": null,
  "is_clip": null,
  "is_short": false,
  "jwplayer_mediaId": null,
  "ladies": false,
  "language": 1,
  "lecture_url": null,
  "location": 0,
  "media": "",
  "meta_tag": "193f37663245b6f0287968b3a3211bbc61781444",
  "no_download": null,
  "on_recent_list": true,
  "org": 0,
  "original_file": null,
  "phone_system_short_extension": "491414",
  "private": false,
  "private_code": null,
  "published_by": 67205,
  "published_by_name": "joshua stern",
  "slug": "horayatdaf-2",
  "speaker": 587,
  "subcategory": 100031,
  "text": null,
  "thumbnail": "2054879996-7f6270915c2d0069a4eb32fbb09c005f79c15dfa86ce247b280cb3d928a128af-d?region=us",
  "thumbnail_url": "https://ta-lectures.s3.us-east-005.backblazeb2.com/thumbnails/391518/391518-t20opm.jpg",
  "title": "Horayat:Daf 2",
  "title_rtl": false,
  "desc": null,
  "video_download_size_string": null,
  "video_download_size": null,
  "vimeo_video": null,
  "vimeo_video_links": [
    "https://proxier.torahanytime.com/aHR0cHM6Ly90YS1sZWN0dXJlcy5zMy51cy1lYXN0LTAwNS5iYWNrYmxhemViMi5jb20vaGxzLzM5MTUxOC90MjBubmovbWFzdGVyLm0zdTg/e3574d95c8adb5524213a30530ec14da21b58b7fae4615f9c75768def508733c.m3u8?has_women=0&speaker_id=587&digest=5c131cacb65de8c5fba2fd6eead0e2bdbc8daef39b312b658c730c14ebe7376d",
    "https://proxier.torahanytime.com/aHR0cHM6Ly90YS1sZWN0dXJlcy5zMy51cy1lYXN0LTAwNS5iYWNrYmxhemViMi5jb20vbXA0LzM5MTUxOC10MjBubmoubXA0/d44e9d195ca9a9649b9e1209aa5f3cbb843a00eb39145f56a34f28bdf4453df9.mp4?has_women=0&speaker_id=587&digest=5c131cacb65de8c5fba2fd6eead0e2bdbc8daef39b312b658c730c14ebe7376d"
  ],
  "vimeo_video_links_legacy": true,
  "vimeo_hash": null,
  "box_id": 1974585198467,
  "publish_by_date": null,
  "date_to_show": "2025-09-03T14:39:24.000Z",
  "is_only_watchable_by_female": false,
  "is_only_listenable_by_female": false,
  "is_only_discoverable_by_female": false,
  "is_only_discoverable_within_org": false,
  "is_not_discoverable": false,
  "m3u8_url": "https://ta-lectures.s3.us-east-005.backblazeb2.com/hls/391518/t20nnj/master.m3u8",
  "mp4_url": "https://ta-lectures.s3.us-east-005.backblazeb2.com/mp4/391518-t20nnj.mp4",
  "mp3_url": "https://ta-lectures.s3.us-east-005.backblazeb2.com/mp3/391518/391518-t20nnj.mp3",
  "watermarked_original_mp4_url": null,
  "ragie_document_id": "795a7c6c-24c9-4fc4-aa08-a69f04b5cd98",
  "created_at": "2025-09-03T14:16:23.000Z",
  "updated_at": "2025-09-03T17:33:03.000Z",
  "deleted_at": null,
  "subcategories": [
    {
      "id": 100031,
      "name": "Horayot",
      "english_name": null
    }
  ],
  "parent_info": null,
  "projects": [
    {
      "id": 1,
      "name": "TorahAnytime"
    }
  ],
  "categories": [
    {
      "id": 18,
      "name": "Daf Yomi/Daily Talmud",
      "english_name": "Talmud"
    }
  ],
  "language_name": "English",
  "speaker_name_first": "Shea",
  "speaker_name_last": "Stern",
  "speaker_photo": "",
  "female": false,
  "view_female_level": 0,
  "speaker_no_download": 0,
  "speaker_title": "Rabbi",
  "speaker_title_short": "R'",
  "video_url": "https://ta-lectures.s3.us-east-005.backblazeb2.com/mp4/391518-t20nnj.mp4",
  "audio_url": "https://ta-lectures.s3.us-east-005.backblazeb2.com/mp3/391518/391518-t20nnj.mp3",
  "proxy_m3u8_url": "https://proxier.torahanytime.com/aHR0cHM6Ly90YS1sZWN0dXJlcy5zMy51cy1lYXN0LTAwNS5iYWNrYmxhemViMi5jb20vaGxzLzM5MTUxOC90MjBubmovbWFzdGVyLm0zdTg/e3574d95c8adb5524213a30530ec14da21b58b7fae4615f9c75768def508733c.m3u8?has_women=0&speaker_id=587&digest=5c131cacb65de8c5fba2fd6eead0e2bdbc8daef39b312b658c730c14ebe7376d",
  "vimeo_proxy_m3u8_url": "https://proxier.torahanytime.com/aHR0cHM6Ly90YS1sZWN0dXJlcy5zMy51cy1lYXN0LTAwNS5iYWNrYmxhemViMi5jb20vaGxzLzM5MTUxOC90MjBubmovbWFzdGVyLm0zdTg/e3574d95c8adb5524213a30530ec14da21b58b7fae4615f9c75768def508733c.m3u8?has_women=0&speaker_id=587&digest=5c131cacb65de8c5fba2fd6eead0e2bdbc8daef39b312b658c730c14ebe7376d",
  "proxy_mp4_url": "https://proxier.torahanytime.com/aHR0cHM6Ly90YS1sZWN0dXJlcy5zMy51cy1lYXN0LTAwNS5iYWNrYmxhemViMi5jb20vbXA0LzM5MTUxOC10MjBubmoubXA0/d44e9d195ca9a9649b9e1209aa5f3cbb843a00eb39145f56a34f28bdf4453df9.mp4?has_women=0&speaker_id=587&digest=5c131cacb65de8c5fba2fd6eead0e2bdbc8daef39b312b658c730c14ebe7376d",
  "likeCount": 0,
  "viewCount": 44
}