{
  "date_created": "2025-10-22T08:58:02.000Z",
  "audio_download_size_string": null,
  "audio_download_size": null,
  "auto_display": false,
  "bitly_audio": "https://mytat.me/a400552",
  "bitly_video": "https://mytat.me/v400552",
  "category": 8,
  "clip_link": null,
  "clip_parent": null,
  "clip_title": null,
  "clipper_email": null,
  "date_recorded": "2025-10-12",
  "dedication": null,
  "display_active": true,
  "duration": 1885,
  "event_speakers": null,
  "host": 0,
  "id": 400552,
  "id_md5": null,
  "is_clip": null,
  "is_short": false,
  "jwplayer_mediaId": null,
  "ladies": false,
  "language": 1,
  "lecture_url": null,
  "location": 0,
  "media": "",
  "meta_tag": "8f997765224c55713ad198ae3bae567cc704e37e",
  "no_download": null,
  "on_recent_list": true,
  "org": 0,
  "original_file": null,
  "phone_system_short_extension": "500412",
  "private": false,
  "private_code": null,
  "published_by": 256769,
  "published_by_name": "shiureiharavbelsky@gmail.com",
  "slug": "sukkot-5786-zeman-simchateinu",
  "speaker": 1128,
  "subcategory": 29,
  "text": null,
  "thumbnail": "2072848629-b199eb00a2b0f7b10fce69d9a921624233b2d5132eb8212523fd0ce425e9773e-d?region=us",
  "thumbnail_url": "https://ta-lectures.s3.us-east-005.backblazeb2.com/thumbnails/400552/400552-t4j0hk.jpg",
  "title": "Sukkot 5786: Zeman Simchateinu",
  "title_rtl": false,
  "desc": null,
  "video_download_size_string": null,
  "video_download_size": null,
  "vimeo_video": null,
  "vimeo_video_links": [
    "https://proxier.torahanytime.com/aHR0cHM6Ly90YS1sZWN0dXJlcy5zMy51cy1lYXN0LTAwNS5iYWNrYmxhemViMi5jb20vaGxzLzQwMDU1Mi90NGl6a3cvbWFzdGVyLm0zdTg/5fec91febbe6de734b1fdb943c92652d592038c3b2d5fe65d3ebe017de4d0c3b.m3u8?has_women=0&speaker_id=1128&digest=fbec8186b6f5555b5018030940d724eecfce891d9ec1417b153cb67b8540c286",
    "https://proxier.torahanytime.com/aHR0cHM6Ly90YS1sZWN0dXJlcy5zMy51cy1lYXN0LTAwNS5iYWNrYmxhemViMi5jb20vbXA0LzQwMDU1Mi10NGl6a3cubXA0/ce6db110b8f69212bf9cbc1b28a5050e62a793534d287c6101a1fce7b7cf2064.mp4?has_women=0&speaker_id=1128&digest=fbec8186b6f5555b5018030940d724eecfce891d9ec1417b153cb67b8540c286"
  ],
  "vimeo_video_links_legacy": true,
  "vimeo_hash": null,
  "box_id": 2023681895603,
  "publish_by_date": "2025-10-22T16:40:00.000Z",
  "date_to_show": "2025-10-22T16:40:00.000Z",
  "is_only_watchable_by_female": false,
  "is_only_listenable_by_female": false,
  "is_only_discoverable_by_female": false,
  "is_only_discoverable_within_org": false,
  "is_not_discoverable": false,
  "m3u8_url": "https://ta-lectures.s3.us-east-005.backblazeb2.com/hls/400552/t4izkw/master.m3u8",
  "mp4_url": "https://ta-lectures.s3.us-east-005.backblazeb2.com/mp4/400552-t4izkw.mp4",
  "mp3_url": "https://ta-lectures.s3.us-east-005.backblazeb2.com/mp3/400552/400552-t4izkw.mp3",
  "watermarked_original_mp4_url": null,
  "ragie_document_id": "c202d1f4-9b27-4850-99e6-b55606fa2bf3",
  "created_at": "2025-10-22T08:58:02.000Z",
  "updated_at": "2025-10-22T17:29:50.000Z",
  "deleted_at": null,
  "subcategories": [
    {
      "id": 29,
      "name": "Sukkot",
      "english_name": "Sukkot"
    }
  ],
  "parent_info": null,
  "projects": [
    {
      "id": 1,
      "name": "TorahAnytime"
    }
  ],
  "categories": [
    {
      "id": 8,
      "name": "Holidays",
      "english_name": "Holidays"
    }
  ],
  "language_name": "English",
  "speaker_name_first": "Daniel",
  "speaker_name_last": "Belsky",
  "speaker_photo": "r-daniel-belsky_54fd02ae-895f-4a24-a490-388ace063328.jpg",
  "female": false,
  "view_female_level": null,
  "speaker_no_download": 0,
  "speaker_title": "Rabbi",
  "speaker_title_short": "R'",
  "video_url": "https://ta-lectures.s3.us-east-005.backblazeb2.com/mp4/400552-t4izkw.mp4",
  "audio_url": "https://ta-lectures.s3.us-east-005.backblazeb2.com/mp3/400552/400552-t4izkw.mp3",
  "proxy_m3u8_url": "https://proxier.torahanytime.com/aHR0cHM6Ly90YS1sZWN0dXJlcy5zMy51cy1lYXN0LTAwNS5iYWNrYmxhemViMi5jb20vaGxzLzQwMDU1Mi90NGl6a3cvbWFzdGVyLm0zdTg/5fec91febbe6de734b1fdb943c92652d592038c3b2d5fe65d3ebe017de4d0c3b.m3u8?has_women=0&speaker_id=1128&digest=fbec8186b6f5555b5018030940d724eecfce891d9ec1417b153cb67b8540c286",
  "vimeo_proxy_m3u8_url": "https://proxier.torahanytime.com/aHR0cHM6Ly90YS1sZWN0dXJlcy5zMy51cy1lYXN0LTAwNS5iYWNrYmxhemViMi5jb20vaGxzLzQwMDU1Mi90NGl6a3cvbWFzdGVyLm0zdTg/5fec91febbe6de734b1fdb943c92652d592038c3b2d5fe65d3ebe017de4d0c3b.m3u8?has_women=0&speaker_id=1128&digest=fbec8186b6f5555b5018030940d724eecfce891d9ec1417b153cb67b8540c286",
  "proxy_mp4_url": "https://proxier.torahanytime.com/aHR0cHM6Ly90YS1sZWN0dXJlcy5zMy51cy1lYXN0LTAwNS5iYWNrYmxhemViMi5jb20vbXA0LzQwMDU1Mi10NGl6a3cubXA0/ce6db110b8f69212bf9cbc1b28a5050e62a793534d287c6101a1fce7b7cf2064.mp4?has_women=0&speaker_id=1128&digest=fbec8186b6f5555b5018030940d724eecfce891d9ec1417b153cb67b8540c286",
  "likeCount": 0,
  "viewCount": 24
}